odoo10_addon_stock_quant_package_product_packaging-10.0.1.1.1-py3.8-nspkg.pth
odoo/addons/stock_quant_package_product_packaging/README.rst
odoo/addons/stock_quant_package_product_packaging/__init__.py
odoo/addons/stock_quant_package_product_packaging/__manifest__.py
odoo/addons/stock_quant_package_product_packaging/i18n/stock_quant_package_product_packaging.pot
odoo/addons/stock_quant_package_product_packaging/models/__init__.py
odoo/addons/stock_quant_package_product_packaging/models/stock_move.py
odoo/addons/stock_quant_package_product_packaging/models/stock_pack_operation.py
odoo/addons/stock_quant_package_product_packaging/models/stock_quant_package.py
odoo/addons/stock_quant_package_product_packaging/readme/CONTRIBUTORS.rst
odoo/addons/stock_quant_package_product_packaging/readme/DESCRIPTION.rst
odoo/addons/stock_quant_package_product_packaging/static/description/icon.png
odoo/addons/stock_quant_package_product_packaging/static/description/index.html
odoo/addons/stock_quant_package_product_packaging/tests/__init__.py
odoo/addons/stock_quant_package_product_packaging/tests/test_stock_quant_package_product_packaging.py
odoo/addons/stock_quant_package_product_packaging/views/stock_quant_package.xml
odoo10_addon_stock_quant_package_product_packaging-10.0.1.1.1.dist-info/METADATA
odoo10_addon_stock_quant_package_product_packaging-10.0.1.1.1.dist-info/WHEEL
odoo10_addon_stock_quant_package_product_packaging-10.0.1.1.1.dist-info/namespace_packages.txt
odoo10_addon_stock_quant_package_product_packaging-10.0.1.1.1.dist-info/top_level.txt
odoo10_addon_stock_quant_package_product_packaging-10.0.1.1.1.dist-info/RECORD
